ckanext/__init__.py
ckanext/composite_search/__init__.py
ckanext/composite_search/interfaces.py
ckanext/composite_search/utils.py
ckanext/composite_search/assets/bundle.css
ckanext/composite_search/assets/bundle.js
ckanext/composite_search/assets/composite_search-module.js
ckanext/composite_search/assets/webassets.yml
ckanext/composite_search/plugin/__init__.py
ckanext/composite_search/plugin/base.py
ckanext/composite_search/plugin/default.py
ckanext/composite_search/tests/__init__.py
ckanext/composite_search/tests/test_plugin.py
ckanext/example_composite_search/__init__.py
ckanext/example_composite_search/plugin.py
ckanext_composite_search-0.4.0.dist-info/METADATA
ckanext_composite_search-0.4.0.dist-info/WHEEL
ckanext_composite_search-0.4.0.dist-info/entry_points.txt
ckanext_composite_search-0.4.0.dist-info/top_level.txt
ckanext_composite_search-0.4.0.dist-info/RECORD
