Metadata-Version: 2.1
Name: ckanext-composite-search
Version: 0.4.0
Author-email: DataShades <datashades@linkdigital.com.au>, Sergey Motornyuk <sergey.motornyuk@linkdigital.com.au>
Maintainer-email: DataShades <datashades@linkdigital.com.au>
License: AGPL
Project-URL: Homepage, https://github.com/DataShades/ckanext-composite-search
Keywords: CKAN
Classifier: Development Status :: 4 - Beta
Classifier: License :: OSI Approved :: GNU Affero General Public License v3 or later (AGPLv3+)
Classifier: Programming Language :: Python :: 3
Provides-Extra: test
Requires-Dist: pytest-ckan ; extra == 'test'
